fastsql/__init__.py
fastsql/_modidx.py
fastsql/core.py
fastsql-2.1.2.dist-info/licenses/LICENSE
fastsql-2.1.2.dist-info/METADATA
fastsql-2.1.2.dist-info/WHEEL
fastsql-2.1.2.dist-info/entry_points.txt
fastsql-2.1.2.dist-info/top_level.txt
fastsql-2.1.2.dist-info/RECORD
