Metadata-Version: 2.4
Name: fastsql
Version: 2.1.2
Summary: A MiniDataAPI spec implementation for SQLAlchemy V2
Author-email: "Jeremy Howard, Daniel Roy Greenfeld, and Answer.AI team" <info@answer.ai>
License: Apache-2.0
Project-URL: Repository, https://github.com/answerdotai/fastsql
Project-URL: Documentation, https://answerdotai.github.io/fastsql
Keywords: nbdev,jupyter,notebook,python
Classifier: Natural Language :: English
Classifier: Intended Audience :: Developers
Classifier: Development Status :: 3 - Alpha
Classifier: Programming Language :: Python :: 3
Classifier: Programming Language :: Python :: 3 :: Only
Requires-Python: >=3.10
License-File: LICENSE
Requires-Dist: fastcore>=1.7.1
Requires-Dist: sqlalchemy
Requires-Dist: sqlparse
Dynamic: license-file
